{
    "content": "Si el usuario consulta sobre nuestros servicios, responderÃ¡s:\n\nÂ¡Bienvenido a nuestros servicios financieros! ğŸŒŸ\n\nEn *GestiÃ³n y Soporte de Proyectos JesÃºs del Gran Poder S.A.*, somos expertos en soluciones financieras ğŸ’¼\n\nğŸ“‹ Nuestros Servicios Principales:\nâ€¢ PrÃ©stamos personalizados\nâ€¢ CrÃ©ditos rÃ¡pidos\nâ€¢ AsesorÃ­a financiera\nâ€¢ Planes de financiamiento flexible\n\nğŸ’¡ Â¿Por quÃ© elegirnos?\nâœ… Soluciones rÃ¡pidas y eficaces\nâœ… AtenciÃ³n personalizada\nâœ… Procesos simplificados\nâœ… Tasas competitivas\n\nğŸ¯ Nos especializamos en:\nâ€¢ PrÃ©stamos para diferentes necesidades\nâ€¢ Opciones adaptadas a tu capacidad de pago\nâ€¢ Plazos flexibles\nâ€¢ Requisitos accesibles\n\nğŸ’ª Nuestro Compromiso:\nâ€¢ Brindar soluciones oportunas\nâ€¢ AcompaÃ±arte en tu crecimiento financiero\nâ€¢ Ofrecer la mejor atenciÃ³n\nâ€¢ Garantizar transparencia en cada proceso\n\nğŸ¤ Â¿Necesitas mÃ¡s informaciÃ³n?\nPuedes iniciar un trÃ¡mite en lÃ­nea o virtual desde aquÃ­ para atenderte y encontrar la mejor soluciÃ³n para ti.\n\nâ­ Â¡En *GestiÃ³n y Soporte de Proyectos JesÃºs del Gran Poder S.A.* tu bienestar financiero es nuestra prioridad!",
    "variaciones": [
        "En *GestiÃ³n y Soporte de Proyectos JesÃºs del Gran Poder S.A.* somos expertos en prÃ©stamos y soluciones financieras rÃ¡pidas. Â¡Conoce nuestras opciones! ğŸ’¼",
        "*GestiÃ³n y Soporte de Proyectos JesÃºs del Gran Poder S.A.* te ofrece prÃ©stamos personalizados, procesos Ã¡giles y atenciÃ³n experta para ti ğŸŒŸ",
        "Descubre las soluciones financieras de *GestiÃ³n y Soporte de Proyectos JesÃºs del Gran Poder S.A.* diseÃ±adas para tu tranquilidad ğŸ’ª"
    ],
    "servicios_destacados": {
        "prestamos": {
            "caracterÃ­sticas": [
                "Personalizados",
                "RÃ¡pidos",
                "Flexibles"
            ],
            "beneficios": [
                "Tasas competitivas",
                "Procesos Ã¡giles",
                "Requisitos accesibles"
            ]
        },
        "asesoria": {
            "tipos": [
                "Financiera personalizada",
                "Planes de pago",
                "GestiÃ³n de crÃ©ditos"
            ]
        }
    },
    "elementos_clave": {
        "emojis": {
            "bienvenida": "ğŸŒŸ",
            "servicios": "ğŸ’¼",
            "lista": "ğŸ“‹",
            "idea": "ğŸ’¡",
            "objetivo": "ğŸ¯",
            "fuerza": "ğŸ’ª",
            "acuerdo": "ğŸ¤",
            "calidad": "â­"
        },
        "puntos_enfasis": [
            "Soluciones rÃ¡pidas",
            "AtenciÃ³n personalizada",
            "Flexibilidad",
            "Compromiso"
        ]
    },
    "tono": "profesional y cercano",
    "objetivo": "informar y generar confianza"
}